[{"clientstore": [["f43",
                   [[[], ["a"], [{"TypeVarType": "a"}],
                     {"FunType": [{"ConType": ["List", [], [{"TypeVarType": "a"}]]},
                                  {"Location": "client"},
                                  {"MonType": {"ConType": ["List", [], [{"TypeVarType": "a"}]]}}]}],
                    [[], ["a"], ["arg1"],
                     {"CodeAbs": [[["arg2",
                                    {"ConType": ["List", [], [{"TypeVarType": "a"}]]}]],
                                  {"ValExpr": {"UnitM": {"Constr": ["Cons", [],
                                                                    [{"TypeVarType": "a"}],
                                                                    [{"Var": "arg1"},
                                                                     {"Var": "arg2"}],
                                                                    [{"TypeVarType": "a"},
                                                                     {"ConType": ["List", [],
                                                                                  [{"TypeVarType": "a"}]]}]]}}}]}]]],
                  ["f44",
                   [[[], ["a"], [],
                     {"FunType": [{"TypeVarType": "a"}, {"Location": "client"},
                                  {"MonType": {"CloType": {"FunType": [{"ConType": ["List", [],
                                                                                    [{"TypeVarType": "a"}]]},
                                                                       {"Location": "client"},
                                                                       {"MonType": {"ConType": ["List",
                                                                                                [],
                                                                                                [{"TypeVarType": "a"}]]}}]}}}]}],
                    [[], ["a"], [],
                     {"CodeAbs": [[["arg1", {"TypeVarType": "a"}]],
                                  {"ValExpr": {"UnitM": {"Closure": [[{"Var": "arg1"}],
                                                                     [{"TypeVarType": "a"}],
                                                                     ["f43", [],
                                                                      [{"TypeVarType": "a"}]],
                                                                     []]}}}]}]]],
                  ["f45",
                   [[[], [], [],
                     {"TypeAbsType": [["a"],
                                      {"MonType": {"CloType": {"FunType": [{"TypeVarType": "a"},
                                                                           {"Location": "client"},
                                                                           {"MonType": {"CloType": {"FunType": [{"ConType": ["List",
                                                                                                                             [],
                                                                                                                             [{"TypeVarType": "a"}]]},
                                                                                                                {"Location": "client"},
                                                                                                                {"MonType": {"ConType": ["List",
                                                                                                                                         [],
                                                                                                                                         [{"TypeVarType": "a"}]]}}]}}}]}}}]}],
                    [[], [], [],
                     {"CodeTypeAbs": [["a"],
                                      {"ValExpr": {"UnitM": {"Closure": [[], [],
                                                                         ["f44", [],
                                                                          [{"TypeVarType": "a"}]],
                                                                         []]}}}]}]]],
                  ["f47",
                   [[[], [], [],
                     {"TypeAbsType": [["a"],
                                      {"MonType": {"ConType": ["List", [],
                                                               [{"TypeVarType": "a"}]]}}]}],
                    [[], [], [],
                     {"CodeTypeAbs": [["a"],
                                      {"ValExpr": {"UnitM": {"Constr": ["Nil", [],
                                                                        [{"TypeVarType": "a"}], [],
                                                                        []]}}}]}]]]],
  "serverstore": [["f43",
                   [[[], ["a"], [{"TypeVarType": "a"}],
                     {"FunType": [{"ConType": ["List", [], [{"TypeVarType": "a"}]]},
                                  {"Location": "client"},
                                  {"MonType": {"ConType": ["List", [], [{"TypeVarType": "a"}]]}}]}],
                    [[], ["a"], ["arg1"],
                     {"CodeAbs": [[["arg2",
                                    {"ConType": ["List", [], [{"TypeVarType": "a"}]]}]],
                                  {"ValExpr": {"UnitM": {"Constr": ["Cons", [],
                                                                    [{"TypeVarType": "a"}],
                                                                    [{"Var": "arg1"},
                                                                     {"Var": "arg2"}],
                                                                    [{"TypeVarType": "a"},
                                                                     {"ConType": ["List", [],
                                                                                  [{"TypeVarType": "a"}]]}]]}}}]}]]],
                  ["f44",
                   [[[], ["a"], [],
                     {"FunType": [{"TypeVarType": "a"}, {"Location": "client"},
                                  {"MonType": {"CloType": {"FunType": [{"ConType": ["List", [],
                                                                                    [{"TypeVarType": "a"}]]},
                                                                       {"Location": "client"},
                                                                       {"MonType": {"ConType": ["List",
                                                                                                [],
                                                                                                [{"TypeVarType": "a"}]]}}]}}}]}],
                    [[], ["a"], [],
                     {"CodeAbs": [[["arg1", {"TypeVarType": "a"}]],
                                  {"ValExpr": {"UnitM": {"Closure": [[{"Var": "arg1"}],
                                                                     [{"TypeVarType": "a"}],
                                                                     ["f43", [],
                                                                      [{"TypeVarType": "a"}]],
                                                                     []]}}}]}]]],
                  ["f45",
                   [[[], [], [],
                     {"TypeAbsType": [["a"],
                                      {"MonType": {"CloType": {"FunType": [{"TypeVarType": "a"},
                                                                           {"Location": "client"},
                                                                           {"MonType": {"CloType": {"FunType": [{"ConType": ["List",
                                                                                                                             [],
                                                                                                                             [{"TypeVarType": "a"}]]},
                                                                                                                {"Location": "client"},
                                                                                                                {"MonType": {"ConType": ["List",
                                                                                                                                         [],
                                                                                                                                         [{"TypeVarType": "a"}]]}}]}}}]}}}]}],
                    [[], [], [],
                     {"CodeTypeAbs": [["a"],
                                      {"ValExpr": {"UnitM": {"Closure": [[], [],
                                                                         ["f44", [],
                                                                          [{"TypeVarType": "a"}]],
                                                                         []]}}}]}]]],
                  ["f47",
                   [[[], [], [],
                     {"TypeAbsType": [["a"],
                                      {"MonType": {"ConType": ["List", [],
                                                               [{"TypeVarType": "a"}]]}}]}],
                    [[], [], [],
                     {"CodeTypeAbs": [["a"],
                                      {"ValExpr": {"UnitM": {"Constr": ["Nil", [],
                                                                        [{"TypeVarType": "a"}], [],
                                                                        []]}}}]}]]]],
  "new": 48},
 {"ValExpr": {"BindM": [[[true, "bogus",
                          {"ConType": ["List", [], [{"ConType": ["Int", [], []]}]]},
                          {"ValExpr": {"BindM": [[[false, "x36",
                                                   {"CloType": {"FunType": [{"ConType": ["List", [],
                                                                                         [{"ConType": ["Int",
                                                                                                       [],
                                                                                                       []]}]]},
                                                                            {"Location": "client"},
                                                                            {"MonType": {"ConType": ["List",
                                                                                                     [],
                                                                                                     [{"ConType": ["Int",
                                                                                                                   [],
                                                                                                                   []]}]]}}]}},
                                                   {"ValExpr": {"BindM": [[[false, "x38",
                                                                            {"CloType": {"FunType": [{"ConType": ["Int",
                                                                                                                  [],
                                                                                                                  []]},
                                                                                                     {"Location": "client"},
                                                                                                     {"MonType": {"CloType": {"FunType": [{"ConType": ["List",
                                                                                                                                                       [],
                                                                                                                                                       [{"ConType": ["Int",
                                                                                                                                                                     [],
                                                                                                                                                                     []]}]]},
                                                                                                                                          {"Location": "client"},
                                                                                                                                          {"MonType": {"ConType": ["List",
                                                                                                                                                                   [],
                                                                                                                                                                   [{"ConType": ["Int",
                                                                                                                                                                                 [],
                                                                                                                                                                                 []]}]]}}]}}}]}},
                                                                            {"ValExpr": {"BindM": [[[false,
                                                                                                     "$x",
                                                                                                     {"CloType": {"FunType": [{"ConType": ["Int",
                                                                                                                                           [],
                                                                                                                                           []]},
                                                                                                                              {"Location": "client"},
                                                                                                                              {"MonType": {"CloType": {"FunType": [{"ConType": ["List",
                                                                                                                                                                                [],
                                                                                                                                                                                [{"ConType": ["Int",
                                                                                                                                                                                              [],
                                                                                                                                                                                              []]}]]},
                                                                                                                                                                   {"Location": "client"},
                                                                                                                                                                   {"MonType": {"ConType": ["List",
                                                                                                                                                                                            [],
                                                                                                                                                                                            [{"ConType": ["Int",
                                                                                                                                                                                                          [],
                                                                                                                                                                                                          []]}]]}}]}}}]}},
                                                                                                     {"TypeApp": [{"Closure": [[],
                                                                                                                               [],
                                                                                                                               ["f45",
                                                                                                                                [],
                                                                                                                                []],
                                                                                                                               []]},
                                                                                                                  {"CloType": {"TypeAbsType": [["a"],
                                                                                                                                               {"MonType": {"CloType": {"FunType": [{"TypeVarType": "a"},
                                                                                                                                                                                    {"Location": "client"},
                                                                                                                                                                                    {"MonType": {"CloType": {"FunType": [{"ConType": ["List",
                                                                                                                                                                                                                                      [],
                                                                                                                                                                                                                                      [{"TypeVarType": "a"}]]},
                                                                                                                                                                                                                         {"Location": "client"},
                                                                                                                                                                                                                         {"MonType": {"ConType": ["List",
                                                                                                                                                                                                                                                  [],
                                                                                                                                                                                                                                                  [{"TypeVarType": "a"}]]}}]}}}]}}}]}},
                                                                                                                  [{"ConType": ["Int",
                                                                                                                                [],
                                                                                                                                []]}]]}]],
                                                                                                   {"ValExpr": {"UnitM": {"Var": "$x"}}}]}}]],
                                                                          {"ValExpr": {"BindM": [[[false,
                                                                                                   "$x",
                                                                                                   {"CloType": {"FunType": [{"ConType": ["List",
                                                                                                                                         [],
                                                                                                                                         [{"ConType": ["Int",
                                                                                                                                                       [],
                                                                                                                                                       []]}]]},
                                                                                                                            {"Location": "client"},
                                                                                                                            {"MonType": {"ConType": ["List",
                                                                                                                                                     [],
                                                                                                                                                     [{"ConType": ["Int",
                                                                                                                                                                   [],
                                                                                                                                                                   []]}]]}}]}},
                                                                                                   {"App": [{"Var": "x38"},
                                                                                                            {"CloType": {"FunType": [{"ConType": ["Int",
                                                                                                                                                  [],
                                                                                                                                                  []]},
                                                                                                                                     {"Location": "client"},
                                                                                                                                     {"MonType": {"CloType": {"FunType": [{"ConType": ["List",
                                                                                                                                                                                       [],
                                                                                                                                                                                       [{"ConType": ["Int",
                                                                                                                                                                                                     [],
                                                                                                                                                                                                     []]}]]},
                                                                                                                                                                          {"Location": "client"},
                                                                                                                                                                          {"MonType": {"ConType": ["List",
                                                                                                                                                                                                   [],
                                                                                                                                                                                                   [{"ConType": ["Int",
                                                                                                                                                                                                                 [],
                                                                                                                                                                                                                 []]}]]}}]}}}]}},
                                                                                                            {"Lit": {"IntLit": 1}}]}]],
                                                                                                 {"ValExpr": {"UnitM": {"Var": "$x"}}}]}}]}}]],
                                                 {"ValExpr": {"BindM": [[[false, "x37",
                                                                          {"ConType": ["List", [],
                                                                                       [{"ConType": ["Int",
                                                                                                     [],
                                                                                                     []]}]]},
                                                                          {"ValExpr": {"BindM": [[[false,
                                                                                                   "$x",
                                                                                                   {"ConType": ["List",
                                                                                                                [],
                                                                                                                [{"ConType": ["Int",
                                                                                                                              [],
                                                                                                                              []]}]]},
                                                                                                   {"TypeApp": [{"Closure": [[],
                                                                                                                             [],
                                                                                                                             ["f47",
                                                                                                                              [],
                                                                                                                              []],
                                                                                                                             []]},
                                                                                                                {"CloType": {"TypeAbsType": [["a"],
                                                                                                                                             {"MonType": {"ConType": ["List",
                                                                                                                                                                      [],
                                                                                                                                                                      [{"TypeVarType": "a"}]]}}]}},
                                                                                                                [{"ConType": ["Int",
                                                                                                                              [],
                                                                                                                              []]}]]}]],
                                                                                                 {"ValExpr": {"UnitM": {"Var": "$x"}}}]}}]],
                                                                        {"App": [{"Var": "x36"},
                                                                                 {"CloType": {"FunType": [{"ConType": ["List",
                                                                                                                       [],
                                                                                                                       [{"ConType": ["Int",
                                                                                                                                     [],
                                                                                                                                     []]}]]},
                                                                                                          {"Location": "client"},
                                                                                                          {"MonType": {"ConType": ["List",
                                                                                                                                   [],
                                                                                                                                   [{"ConType": ["Int",
                                                                                                                                                 [],
                                                                                                                                                 []]}]]}}]}},
                                                                                 {"Var": "x37"}]}]}}]}}]],
                        {"ValExpr": {"UnitM": {"Lit": "UnitLit"}}}]}}]